mcdiscovery/__init__.py
mcdiscovery/__main__.py
mcdiscovery/metadata.py
mcdiscovery/net.py
mcdiscovery/types/__init__.py
mcdiscovery/types/local_server.py
mcdiscovery-0.1.1.dist-info/LICENSE
mcdiscovery-0.1.1.dist-info/WHEEL
mcdiscovery-0.1.1.dist-info/METADATA
mcdiscovery-0.1.1.dist-info/RECORD
